fastnc/__init__.py
fastnc/bispectrum.py
fastnc/coupling.py
fastnc/devtool.py
fastnc/fastnc.py
fastnc/fftlog.py
fastnc/halofit.py
fastnc/integration.py
fastnc/multipole.py
fastnc/onejnc.py
fastnc/trigutils.py
fastnc/twobessel.py
fastnc/utils.py
fastnc-1.1.22.dist-info/LICENSE
fastnc-1.1.22.dist-info/METADATA
fastnc-1.1.22.dist-info/WHEEL
fastnc-1.1.22.dist-info/top_level.txt
fastnc-1.1.22.dist-info/RECORD
