Metadata-Version: 2.1
Name: fastnc
Version: 1.1.22
Summary: fastnc package
Home-page: https://github.com/git-sunao/fastnc
Author: Sunao Sugiyama, Rafael Heringer Gomes
Author-email: sunaosugiyama@gmail.com
Keywords: cosmology,large scale structure,three-point correlation function
Classifier: Programming Language :: Python :: 3
License-File: LICENSE
Requires-Dist: numpy
Requires-Dist: scipy
Requires-Dist: astropy
Requires-Dist: pandas
Requires-Dist: mpi4py
